__init__.py
pineaprint/__init__.py
pineaprint-1.0.3.dist-info/LICENSE.txt
pineaprint-1.0.3.dist-info/METADATA
pineaprint-1.0.3.dist-info/WHEEL
pineaprint-1.0.3.dist-info/top_level.txt
pineaprint-1.0.3.dist-info/RECORD
