Metadata-Version: 2.1
Name: pineaprint
Version: 1.0.3
Summary: Easily print a complex data structure for readability
Home-page: UNKNOWN
Author: PineappleFan
Author-email: pineapplefanyt@gmail.com
License: UNKNOWN
Keywords: prettyprint,devtools,utilities
Platform: UNKNOWN
Classifier: Development Status :: 4 - Beta
Classifier: Intended Audience :: Developers
Classifier: Topic :: Utilities
Classifier: License :: OSI Approved :: MIT License
Classifier: Programming Language :: Python :: 3
Classifier: Programming Language :: Python :: 3.6
Classifier: Programming Language :: Python :: 3.7
Classifier: Programming Language :: Python :: 3.8
Classifier: Programming Language :: Python :: 3.9
Classifier: Programming Language :: Python :: 3 :: Only
Requires-Python: >=3.7, <4
